[
    {
        "user": "U041CL6454N",
        "type": "message",
        "ts": "1681993225.393239",
        "client_msg_id": "b3cd1102-9f66-41bc-8ae0-67bd5f7f3410",
        "text": "<@U01DZUA88S1> it is long since I last looked at this bug, thanks to some problems in my R build. I am now in a state of committing the corrections as I mentioned earlier above. I just have one query, while writing the tests for my corrections, shall I add the tests in `..\/tests\/lm-tests.R` ?",
        "team": "T01DW9DLB2A",
        "user_team": "T01DW9DLB2A",
        "source_team": "T01DW9DLB2A",
        "user_profile": {
            "avatar_hash": "0e3d8ea67951",
            "image_72": "https:\/\/avatars.slack-edge.com\/2023-01-24\/4687497652629_0e3d8ea67951340d9e0a_72.jpg",
            "first_name": "Debartha",
            "real_name": "Debartha Paul",
            "display_name": "Debartha Paul",
            "team": "T01DW9DLB2A",
            "name": "pauldeep102",
            "is_restricted": false,
            "is_ultra_restricted": false
        },
        "thread_ts": "1675673716.107509",
        "parent_user_id": "U01DZUA88S1",
        "blocks": [
            {
                "type": "rich_text",
                "block_id": "kgD",
                "elements": [
                    {
                        "type": "rich_text_section",
                        "elements": [
                            {
                                "type": "user",
                                "user_id": "U01DZUA88S1"
                            },
                            {
                                "type": "text",
                                "text": " it is long since I last looked at this bug, thanks to some problems in my R build. I am now in a state of committing the corrections as I mentioned earlier above. I just have one query, while writing the tests for my corrections, shall I add the tests in "
                            },
                            {
                                "type": "text",
                                "text": "..\/tests\/lm-tests.R",
                                "style": {
                                    "code": true
                                }
                            },
                            {
                                "type": "text",
                                "text": " ?"
                            }
                        ]
                    }
                ]
            }
        ]
    }
]