[
    {
        "text": "I finished cleanup up all `tools::checkPoFiles` and `msgfmt` issues, also deleted the dummy PO files without any translation for the sake of a patch, and still generated a huge patch file (attached).\nskimming through looks promising -- except for long lines retruncated, which is probably unwanted diff. I'll try to fix that.\ncc <@U01N3ET8N82> to take a look at the patch file and :pray:\nalso saw <@U07BR2DAFNK>’s email on offering help -- that's super highly appreciated. it will be very nice if we can reduce the bottleneck on my and Mike's availability.",
        "files": [
            {
                "id": "F0ATD3M4M5M",
                "created": 1776554110,
                "timestamp": 1776554110,
                "mimetype": "application\/x-gzip",
                "filetype": "gzip",
                "pretty_type": "Gzip",
                "user": "U027JEHGZRA",
                "user_team": "T01DW9DLB2A",
                "editable": false,
                "size": 1950945,
                "mode": "hosted",
                "is_external": false,
                "external_type": "",
                "is_public": true,
                "public_url_shared": false,
                "display_as_bot": false,
                "username": "",
                "name": "r-translations-20260419.patch.gz",
                "title": "r-translations-20260419.patch.gz",
                "is_modified_by_ai": false,
                "url_private": "https:\/\/files.slack.com\/files-pri\/T01DW9DLB2A-F0ATD3M4M5M\/r-translations-20260419.patch.gz?token=xoxe-1472319691078-11457733709559-11476879211236-1668ffb159b44316fae6b97e1a96cc45",
                "url_private_download": "https:\/\/files.slack.com\/files-pri\/T01DW9DLB2A-F0ATD3M4M5M\/download\/r-translations-20260419.patch.gz?token=xoxe-1472319691078-11457733709559-11476879211236-1668ffb159b44316fae6b97e1a96cc45",
                "media_display_type": "unknown",
                "permalink": "https:\/\/r-contributors.slack.com\/files\/U01DZUA88S1\/F0ATD3M4M5M\/r-translations-20260419.patch.gz",
                "permalink_public": "https:\/\/slack-files.com\/T01DW9DLB2A-F0ATD3M4M5M-3301821615",
                "is_starred": false,
                "skipped_shares": true,
                "has_rich_preview": false,
                "file_access": "visible"
            }
        ],
        "upload": false,
        "user": "U027JEHGZRA",
        "display_as_bot": false,
        "blocks": [
            {
                "type": "rich_text",
                "block_id": "vrZ5N",
                "elements": [
                    {
                        "type": "rich_text_section",
                        "elements": [
                            {
                                "type": "text",
                                "text": "I finished cleanup up all "
                            },
                            {
                                "type": "text",
                                "text": "tools::checkPoFiles",
                                "style": {
                                    "code": true
                                }
                            },
                            {
                                "type": "text",
                                "text": " and "
                            },
                            {
                                "type": "text",
                                "text": "msgfmt",
                                "style": {
                                    "code": true
                                }
                            },
                            {
                                "type": "text",
                                "text": " issues, also deleted the dummy PO files without any translation for the sake of a patch, and still generated a huge patch file (attached).\nskimming through looks promising -- except for long lines retruncated, which is probably unwanted diff. I'll try to fix that.\ncc "
                            },
                            {
                                "type": "user",
                                "user_id": "U01N3ET8N82"
                            },
                            {
                                "type": "text",
                                "text": " to take a look at the patch file and "
                            },
                            {
                                "type": "emoji",
                                "name": "pray",
                                "unicode": "1f64f"
                            },
                            {
                                "type": "text",
                                "text": "\nalso saw "
                            },
                            {
                                "type": "user",
                                "user_id": "U07BR2DAFNK"
                            },
                            {
                                "type": "text",
                                "text": "’s email on offering help -- that's super highly appreciated. it will be very nice if we can reduce the bottleneck on my and Mike's availability."
                            }
                        ]
                    }
                ]
            }
        ],
        "subtype": "thread_broadcast",
        "root": {
            "user": "U01DZUA88S1",
            "type": "message",
            "ts": "1776090245.589669",
            "client_msg_id": "79415ec0-9ed9-4aec-92a6-341e902b5a74",
            "text": "<@U027JEHGZRA> <@U01N3ET8N82> <@U07BR2DAFNK> I think we may have missed the window for submitting a translation patch for R 4.6.0, as the feature freeze was last Friday (<https:\/\/developer.r-project.org\/>). On the other hand, the POT files have not been updated in the SVN since the update on 7 Mar, so maybe if it is is possible to create a quick patch, there is time to submit before the code freeze on Friday? What do you think <@U01JACR6L7L>?\n\nIn any case, the Weblate seems to be locked again, so it requires another look.",
            "team": "T01DW9DLB2A",
            "thread_ts": "1776090245.589669",
            "reply_count": 24,
            "reply_users_count": 5,
            "latest_reply": "1776590011.528759",
            "reply_users": [
                "U01N3ET8N82",
                "U01JACR6L7L",
                "U027JEHGZRA",
                "U01DZUA88S1",
                "U0524MK6H3K"
            ],
            "replies": [
                {
                    "user": "U01N3ET8N82",
                    "ts": "1776090588.802159"
                },
                {
                    "user": "U01JACR6L7L",
                    "ts": "1776095617.154929"
                },
                {
                    "user": "U027JEHGZRA",
                    "ts": "1776117544.866459"
                },
                {
                    "user": "U01DZUA88S1",
                    "ts": "1776153571.227369"
                },
                {
                    "user": "U027JEHGZRA",
                    "ts": "1776154684.923869"
                },
                {
                    "user": "U027JEHGZRA",
                    "ts": "1776176461.054829"
                },
                {
                    "user": "U027JEHGZRA",
                    "ts": "1776176755.298019"
                },
                {
                    "user": "U027JEHGZRA",
                    "ts": "1776179393.711869"
                },
                {
                    "user": "U01N3ET8N82",
                    "ts": "1776179967.013899"
                },
                {
                    "user": "U01N3ET8N82",
                    "ts": "1776179997.609529"
                },
                {
                    "user": "U027JEHGZRA",
                    "ts": "1776180116.189259"
                },
                {
                    "user": "U027JEHGZRA",
                    "ts": "1776181932.688059"
                },
                {
                    "user": "U027JEHGZRA",
                    "ts": "1776203515.719089"
                },
                {
                    "user": "U027JEHGZRA",
                    "ts": "1776203780.811299"
                },
                {
                    "user": "U027JEHGZRA",
                    "ts": "1776204843.705039"
                },
                {
                    "user": "U027JEHGZRA",
                    "ts": "1776240297.166889"
                },
                {
                    "user": "U027JEHGZRA",
                    "ts": "1776288445.056389"
                },
                {
                    "user": "U01JACR6L7L",
                    "ts": "1776289240.091189"
                },
                {
                    "user": "U027JEHGZRA",
                    "ts": "1776379889.354339"
                },
                {
                    "user": "U027JEHGZRA",
                    "ts": "1776554263.341509"
                },
                {
                    "user": "U0524MK6H3K",
                    "ts": "1776580335.192209"
                },
                {
                    "user": "U027JEHGZRA",
                    "ts": "1776588190.029769"
                },
                {
                    "user": "U027JEHGZRA",
                    "ts": "1776589974.625319"
                },
                {
                    "user": "U027JEHGZRA",
                    "ts": "1776590011.528759"
                }
            ],
            "is_locked": false,
            "subscribed": true,
            "last_read": "1776590011.528759",
            "blocks": [
                {
                    "type": "rich_text",
                    "block_id": "7AWWY",
                    "elements": [
                        {
                            "type": "rich_text_section",
                            "elements": [
                                {
                                    "type": "user",
                                    "user_id": "U027JEHGZRA"
                                },
                                {
                                    "type": "text",
                                    "text": " "
                                },
                                {
                                    "type": "user",
                                    "user_id": "U01N3ET8N82"
                                },
                                {
                                    "type": "text",
                                    "text": " "
                                },
                                {
                                    "type": "user",
                                    "user_id": "U07BR2DAFNK"
                                },
                                {
                                    "type": "text",
                                    "text": " I think we may have missed the window for submitting a translation patch for R 4.6.0, as the feature freeze was last Friday ("
                                },
                                {
                                    "type": "link",
                                    "url": "https:\/\/developer.r-project.org\/"
                                },
                                {
                                    "type": "text",
                                    "text": "). On the other hand, the POT files have not been updated in the SVN since the update on 7 Mar, so maybe if it is is possible to create a quick patch, there is time to submit before the code freeze on Friday? What do you think "
                                },
                                {
                                    "type": "user",
                                    "user_id": "U01JACR6L7L"
                                },
                                {
                                    "type": "text",
                                    "text": "?\n\nIn any case, the Weblate seems to be locked again, so it requires another look."
                                }
                            ]
                        }
                    ]
                }
            ]
        },
        "type": "message",
        "ts": "1776554263.341509",
        "client_msg_id": "7879e946-8f05-46cd-ab53-f30d2b1491c4",
        "thread_ts": "1776090245.589669",
        "parent_user_id": "U01DZUA88S1"
    },
    {
        "user": "U0524MK6H3K",
        "type": "message",
        "ts": "1776580335.192209",
        "client_msg_id": "4b567f91-389d-4e29-b0c1-dae85e20ee0b",
        "text": "When I submitted translation patches manually, it helped to run `msgfmt -w 79` or `msgfmt --no-wrap` depending on whether the `*.po` file in the repository originally had any lines longer than 79 characters.",
        "team": "T01DW9DLB2A",
        "user_team": "T01DW9DLB2A",
        "source_team": "T01DW9DLB2A",
        "user_profile": {
            "avatar_hash": "gc7f0c5d391a",
            "image_72": "https:\/\/secure.gravatar.com\/avatar\/c7f0c5d391a6f869c9310694b55fa506.jpg?s=72&d=https%3A%2F%2Fa.slack-edge.com%2Fdf10d%2Fimg%2Favatars%2Fava_0018-72.png",
            "first_name": "Ivan",
            "real_name": "Ivan Krylov",
            "display_name": "Ivan Krylov",
            "team": "T01DW9DLB2A",
            "name": "ikrylov",
            "is_restricted": false,
            "is_ultra_restricted": false
        },
        "thread_ts": "1776090245.589669",
        "parent_user_id": "U01DZUA88S1",
        "blocks": [
            {
                "type": "rich_text",
                "block_id": "oDLfy",
                "elements": [
                    {
                        "type": "rich_text_section",
                        "elements": [
                            {
                                "type": "text",
                                "text": "When I submitted translation patches manually, it helped to run "
                            },
                            {
                                "type": "text",
                                "text": "msgfmt -w 79",
                                "style": {
                                    "code": true
                                }
                            },
                            {
                                "type": "text",
                                "text": " or "
                            },
                            {
                                "type": "text",
                                "text": "msgfmt --no-wrap",
                                "style": {
                                    "code": true
                                }
                            },
                            {
                                "type": "text",
                                "text": " depending on whether the "
                            },
                            {
                                "type": "text",
                                "text": "*.po",
                                "style": {
                                    "code": true
                                }
                            },
                            {
                                "type": "text",
                                "text": " file in the repository originally had any lines longer than 79 characters."
                            }
                        ]
                    }
                ]
            }
        ]
    }
]