[
    {
        "user": "U02SRPRJN69",
        "type": "message",
        "ts": "1723257660.258369",
        "edited": {
            "user": "U02SRPRJN69",
            "ts": "1723523024.000000"
        },
        "client_msg_id": "acf6cc74-08b1-41cc-ae61-b5d1a2914884",
        "text": "I threw together a quick demo presentation using `quarto-live` on a common DS concept: Linear Regression. If you're prepping for a fall course, definitely consider including the new technology in your course stack!\n\nLive page: <https:\/\/tutorials.thecoatlessprofessor.com\/next-gen-data-science-education-wasm\/>\nRepo: <https:\/\/github.com\/coatless-tutorials\/next-gen-data-science-education-wasm>",
        "team": "T01DW9DLB2A",
        "user_team": "T01DW9DLB2A",
        "source_team": "T01DW9DLB2A",
        "user_profile": {
            "avatar_hash": "b565fd6b2986",
            "image_72": "https:\/\/avatars.slack-edge.com\/2022-06-24\/3741856922896_b565fd6b29864a84fbaa_72.jpg",
            "first_name": "James",
            "real_name": "James Balamuta",
            "display_name": "jjb",
            "team": "T01DW9DLB2A",
            "name": "balamut2",
            "is_restricted": false,
            "is_ultra_restricted": false
        },
        "attachments": [
            {
                "id": 1,
                "color": "24292f",
                "bot_id": "B01V53YD4FJ",
                "app_unfurl_url": "https:\/\/github.com\/coatless-tutorials\/next-gen-data-science-education-wasm",
                "is_app_unfurl": true,
                "app_id": "A01BP7R4KNY",
                "fallback": "coatless-tutorials\/next-gen-data-science-education-wasm",
                "text": "This repository contains a code powering the \"Next-Generation Data Science Education with WebAssembly\" demonstration.",
                "title": "coatless-tutorials\/next-gen-data-science-education-wasm",
                "fields": [
                    {
                        "value": "<https:\/\/tutorials.thecoatlessprofessor.com\/next-gen-data-science-education-wasm\/>",
                        "title": "Website",
                        "short": true
                    },
                    {
                        "value": "1",
                        "title": "Stars",
                        "short": true
                    }
                ]
            }
        ],
        "blocks": [
            {
                "type": "rich_text",
                "block_id": "etBtu",
                "elements": [
                    {
                        "type": "rich_text_section",
                        "elements": [
                            {
                                "type": "text",
                                "text": "I threw together a quick demo presentation using "
                            },
                            {
                                "type": "text",
                                "text": "quarto-live",
                                "style": {
                                    "code": true
                                }
                            },
                            {
                                "type": "text",
                                "text": " on a common DS concept: Linear Regression. If you're prepping for a fall course, definitely consider including the new technology in your course stack!\n\nLive page: "
                            },
                            {
                                "type": "link",
                                "url": "https:\/\/tutorials.thecoatlessprofessor.com\/next-gen-data-science-education-wasm\/"
                            },
                            {
                                "type": "text",
                                "text": "\nRepo: "
                            },
                            {
                                "type": "link",
                                "url": "https:\/\/github.com\/coatless-tutorials\/next-gen-data-science-education-wasm"
                            }
                        ]
                    }
                ]
            }
        ],
        "reactions": [
            {
                "name": "+1::skin-tone-2",
                "users": [
                    "U01DZUA88S1"
                ],
                "count": 1
            }
        ]
    }
]