[
    {
        "subtype": "bot_message",
        "text": "*[Bug 19054] all(&lt;symbol&gt;) can lead to ASAN error (out-of-bounds read)*\n<https:\/\/bugs.r-project.org\/show_bug.cgi?id=19054>\n\nMartin Maechler (<mailto:maechler@stat.math.ethz.ch|maechler@stat.math.ethz.ch>) changed:\n\n           What    |Removed                     |Added\n----------------------------------------------------------------------------\n             Status|CONFIRMED                   |CLOSED\n         Resolution|---                         |FIXED\n\n--- Comment #3 from Martin Maechler (<mailto:maechler@stat.math.ethz.ch|maechler@stat.math.ethz.ch>) ---\nFixed already a while ago  (svn r89986 | 2026-04-30), and even backported to R\n4.6.0 patched, a week ago.",
        "username": "r-bugs notifier",
        "icons": {
            "emoji": ":robot_face:"
        },
        "type": "message",
        "ts": "1780326142.146219",
        "bot_id": "B06769YJX9Q",
        "app_id": "A024R9PQM",
        "blocks": [
            {
                "type": "rich_text",
                "block_id": "BSR7e",
                "elements": [
                    {
                        "type": "rich_text_section",
                        "elements": [
                            {
                                "type": "text",
                                "text": "[Bug 19054] all(<symbol>) can lead to ASAN error (out-of-bounds read)",
                                "style": {
                                    "bold": true
                                }
                            },
                            {
                                "type": "text",
                                "text": "\n"
                            },
                            {
                                "type": "link",
                                "url": "https:\/\/bugs.r-project.org\/show_bug.cgi?id=19054"
                            },
                            {
                                "type": "text",
                                "text": "\n\nMartin Maechler ("
                            },
                            {
                                "type": "link",
                                "url": "mailto:maechler@stat.math.ethz.ch",
                                "text": "maechler@stat.math.ethz.ch",
                                "unsafe": true
                            },
                            {
                                "type": "text",
                                "text": ") changed:\n\n           What    |Removed                     |Added\n----------------------------------------------------------------------------\n             Status|CONFIRMED                   |CLOSED\n         Resolution|---                         |FIXED\n\n--- Comment #3 from Martin Maechler ("
                            },
                            {
                                "type": "link",
                                "url": "mailto:maechler@stat.math.ethz.ch",
                                "text": "maechler@stat.math.ethz.ch",
                                "unsafe": true
                            },
                            {
                                "type": "text",
                                "text": ") ---\nFixed already a while ago  (svn r89986 | 2026-04-30), and even backported to R\n4.6.0 patched, a week ago."
                            }
                        ]
                    }
                ]
            }
        ]
    },
    {
        "subtype": "bot_message",
        "text": "*[Bug 19068] `dev.capabilities()` reports wrong transparency values for BMP\/JPEG\/TIFF formats for cairo and Xlib types*\n<https:\/\/bugs.r-project.org\/show_bug.cgi?id=19068>\n\nMartin Maechler (<mailto:maechler@stat.math.ethz.ch|maechler@stat.math.ethz.ch>) changed:\n\n           What    |Removed                     |Added\n----------------------------------------------------------------------------\n     Ever confirmed|0                           |1\n                 CC|                            |maechler@stat.math.ethz.ch\n             Status|UNCONFIRMED                 |CONFIRMED\n\n--- Comment #2 from Martin Maechler (<mailto:maechler@stat.math.ethz.ch|maechler@stat.math.ethz.ch>) ---\nThank you, Trevor.\nYour proposal makes sense to me, and the patch looks simple and short enough\n... though I'd __really__ be grateful if you used _sensible_ file names for\npatch files (`patch.diff` is really like calling your dog \"dog\" ..).\n\nOTOH, others (inside and out of R-core) may know more about this \nand why this was not in R's `grDevices` till now.\n\nIn any case, I'm happy to _confirm_ this formally.",
        "username": "r-bugs notifier",
        "icons": {
            "emoji": ":robot_face:"
        },
        "type": "message",
        "ts": "1780326355.866199",
        "bot_id": "B06769YJX9Q",
        "app_id": "A024R9PQM",
        "blocks": [
            {
                "type": "rich_text",
                "block_id": "YK9aR",
                "elements": [
                    {
                        "type": "rich_text_section",
                        "elements": [
                            {
                                "type": "text",
                                "text": "[Bug 19068] ",
                                "style": {
                                    "bold": true
                                }
                            },
                            {
                                "type": "text",
                                "text": "dev.capabilities()",
                                "style": {
                                    "bold": true,
                                    "code": true
                                }
                            },
                            {
                                "type": "text",
                                "text": " reports wrong transparency values for BMP\/JPEG\/TIFF formats for cairo and Xlib types",
                                "style": {
                                    "bold": true
                                }
                            },
                            {
                                "type": "text",
                                "text": "\n"
                            },
                            {
                                "type": "link",
                                "url": "https:\/\/bugs.r-project.org\/show_bug.cgi?id=19068"
                            },
                            {
                                "type": "text",
                                "text": "\n\nMartin Maechler ("
                            },
                            {
                                "type": "link",
                                "url": "mailto:maechler@stat.math.ethz.ch",
                                "text": "maechler@stat.math.ethz.ch",
                                "unsafe": true
                            },
                            {
                                "type": "text",
                                "text": ") changed:\n\n           What    |Removed                     |Added\n----------------------------------------------------------------------------\n     Ever confirmed|0                           |1\n                 CC|                            |maechler@stat.math.ethz.ch\n             Status|UNCONFIRMED                 |CONFIRMED\n\n--- Comment #2 from Martin Maechler ("
                            },
                            {
                                "type": "link",
                                "url": "mailto:maechler@stat.math.ethz.ch",
                                "text": "maechler@stat.math.ethz.ch",
                                "unsafe": true
                            },
                            {
                                "type": "text",
                                "text": ") ---\nThank you, Trevor.\nYour proposal makes sense to me, and the patch looks simple and short enough\n... though I'd __really__ be grateful if you used "
                            },
                            {
                                "type": "text",
                                "text": "sensible",
                                "style": {
                                    "italic": true
                                }
                            },
                            {
                                "type": "text",
                                "text": " file names for\npatch files ("
                            },
                            {
                                "type": "text",
                                "text": "patch.diff",
                                "style": {
                                    "code": true
                                }
                            },
                            {
                                "type": "text",
                                "text": " is really like calling your dog \"dog\" ..).\n\nOTOH, others (inside and out of R-core) may know more about this \nand why this was not in R's "
                            },
                            {
                                "type": "text",
                                "text": "grDevices",
                                "style": {
                                    "code": true
                                }
                            },
                            {
                                "type": "text",
                                "text": " till now.\n\nIn any case, I'm happy to "
                            },
                            {
                                "type": "text",
                                "text": "confirm",
                                "style": {
                                    "italic": true
                                }
                            },
                            {
                                "type": "text",
                                "text": " this formally."
                            }
                        ]
                    }
                ]
            }
        ]
    },
    {
        "subtype": "bot_message",
        "text": "*[Bug 19029] Overly-long dlerror() may corrupt dyn.load() state*\n<https:\/\/bugs.r-project.org\/show_bug.cgi?id=19029>\n\n--- Comment #2 from Ivan Krylov (<mailto:ikrylov@disroot.org|ikrylov@disroot.org>) ---\nSince the glibc `dlerror()` includes the full path to the shared object that\nfailed to load, an easy reproducer on Linux\/glibc is just\n`try(dyn.load(strrep(\"A\", 1000))); library(Matrix)`.",
        "username": "r-bugs notifier",
        "icons": {
            "emoji": ":robot_face:"
        },
        "type": "message",
        "ts": "1780328832.446249",
        "bot_id": "B06769YJX9Q",
        "app_id": "A024R9PQM",
        "blocks": [
            {
                "type": "rich_text",
                "block_id": "no6s3",
                "elements": [
                    {
                        "type": "rich_text_section",
                        "elements": [
                            {
                                "type": "text",
                                "text": "[Bug 19029] Overly-long dlerror() may corrupt dyn.load() state",
                                "style": {
                                    "bold": true
                                }
                            },
                            {
                                "type": "text",
                                "text": "\n"
                            },
                            {
                                "type": "link",
                                "url": "https:\/\/bugs.r-project.org\/show_bug.cgi?id=19029"
                            },
                            {
                                "type": "text",
                                "text": "\n\n--- Comment #2 from Ivan Krylov ("
                            },
                            {
                                "type": "link",
                                "url": "mailto:ikrylov@disroot.org",
                                "text": "ikrylov@disroot.org"
                            },
                            {
                                "type": "text",
                                "text": ") ---\nSince the glibc "
                            },
                            {
                                "type": "text",
                                "text": "dlerror()",
                                "style": {
                                    "code": true
                                }
                            },
                            {
                                "type": "text",
                                "text": " includes the full path to the shared object that\nfailed to load, an easy reproducer on Linux\/glibc is just\n"
                            },
                            {
                                "type": "text",
                                "text": "try(dyn.load(strrep(\"A\", 1000))); library(Matrix)",
                                "style": {
                                    "code": true
                                }
                            },
                            {
                                "type": "text",
                                "text": "."
                            }
                        ]
                    }
                ]
            }
        ]
    }
]