[
    {
        "user": "U06360JH6FP",
        "type": "message",
        "ts": "1705047193.276199",
        "client_msg_id": "c1c572b6-72db-4019-a429-577a8c3233a7",
        "text": "<@U06D8CVMZDG> I tried circumventing the requirement by setting up to just submit from my laptops own terminal by installing check50 and submit50 but even then I needed to give private repo access because the corresponding account created in github ME50 is a private repo. Anyway, I’m now set up work either locally with my own tools or with the CS50 vs code setup so alls good.",
        "team": "T01DW9DLB2A",
        "user_team": "T01DW9DLB2A",
        "source_team": "T01DW9DLB2A",
        "user_profile": {
            "avatar_hash": "ccd10a98f3a6",
            "image_72": "https:\/\/avatars.slack-edge.com\/2023-10-28\/6123580324497_ccd10a98f3a6190d4dd5_72.jpg",
            "first_name": "Munawar",
            "real_name": "Munawar Cheema",
            "display_name": "Munawar Cheema",
            "team": "T01DW9DLB2A",
            "name": "munawar.a.cheema",
            "is_restricted": false,
            "is_ultra_restricted": false
        },
        "thread_ts": "1704894218.345369",
        "parent_user_id": "U06D8CVMZDG",
        "blocks": [
            {
                "type": "rich_text",
                "block_id": "b5Oai",
                "elements": [
                    {
                        "type": "rich_text_section",
                        "elements": [
                            {
                                "type": "user",
                                "user_id": "U06D8CVMZDG"
                            },
                            {
                                "type": "text",
                                "text": " I tried circumventing the requirement by setting up to just submit from my laptops own terminal by installing check50 and submit50 but even then I needed to give private repo access because the corresponding account created in github ME50 is a private repo. Anyway, I’m now set up work either locally with my own tools or with the CS50 vs code setup so alls good."
                            }
                        ]
                    }
                ]
            }
        ]
    },
    {
        "user": "U06360JH6FP",
        "type": "message",
        "ts": "1705048935.044139",
        "edited": {
            "user": "U06360JH6FP",
            "ts": "1705086856.000000"
        },
        "client_msg_id": "be808779-0ce2-4cea-90d6-6b7dd341e575",
        "text": "<@U01DZUA88S1> from the first lecture it seems to me we will be using C99 for this course. If that is indeed the case, it might be worth highlighting that Modern C was based on C11, and consequently using any code idioms from that book which use unique features of C11 will likely not pass the automated checks of CS50.",
        "team": "T01DW9DLB2A",
        "user_team": "T01DW9DLB2A",
        "source_team": "T01DW9DLB2A",
        "user_profile": {
            "avatar_hash": "ccd10a98f3a6",
            "image_72": "https:\/\/avatars.slack-edge.com\/2023-10-28\/6123580324497_ccd10a98f3a6190d4dd5_72.jpg",
            "first_name": "Munawar",
            "real_name": "Munawar Cheema",
            "display_name": "Munawar Cheema",
            "team": "T01DW9DLB2A",
            "name": "munawar.a.cheema",
            "is_restricted": false,
            "is_ultra_restricted": false
        },
        "thread_ts": "1704974666.173399",
        "parent_user_id": "U01DZUA88S1",
        "blocks": [
            {
                "type": "rich_text",
                "block_id": "KVzsQ",
                "elements": [
                    {
                        "type": "rich_text_section",
                        "elements": [
                            {
                                "type": "user",
                                "user_id": "U01DZUA88S1"
                            },
                            {
                                "type": "text",
                                "text": " from the first lecture it seems to me we will be using C99 for this course. If that is indeed the case, it might be worth highlighting that Modern C was based on C11, and consequently using any code idioms from that book which use unique features of C11 will likely not pass the automated checks of CS50."
                            }
                        ]
                    }
                ]
            }
        ]
    },
    {
        "user": "U01DZUA88S1",
        "type": "message",
        "ts": "1705051142.035629",
        "client_msg_id": "b1a2213a-2a96-4d1d-a44d-b92a161cbc34",
        "text": "Thanks for the heads up <@U06360JH6FP>",
        "team": "T01DW9DLB2A",
        "user_team": "T01DW9DLB2A",
        "source_team": "T01DW9DLB2A",
        "user_profile": {
            "avatar_hash": "g580131f5a7a",
            "image_72": "https:\/\/secure.gravatar.com\/avatar\/580131f5a7a4fa33c811dc6d20ab3ef8.jpg?s=72&d=https%3A%2F%2Fa.slack-edge.com%2Fdf10d%2Fimg%2Favatars%2Fava_0004-72.png",
            "first_name": "Heather",
            "real_name": "Heather Turner (she\/her)",
            "display_name": "Heather Turner",
            "team": "T01DW9DLB2A",
            "name": "ht",
            "is_restricted": false,
            "is_ultra_restricted": false
        },
        "thread_ts": "1704974666.173399",
        "parent_user_id": "U01DZUA88S1",
        "blocks": [
            {
                "type": "rich_text",
                "block_id": "ZN2dz",
                "elements": [
                    {
                        "type": "rich_text_section",
                        "elements": [
                            {
                                "type": "text",
                                "text": "Thanks for the heads up "
                            },
                            {
                                "type": "user",
                                "user_id": "U06360JH6FP"
                            }
                        ]
                    }
                ]
            }
        ]
    },
    {
        "user": "U035M81N341",
        "type": "message",
        "ts": "1705076353.136199",
        "edited": {
            "user": "U035M81N341",
            "ts": "1705076474.000000"
        },
        "client_msg_id": "6e190409-b52d-40b7-b7fa-8ae3e085eff6",
        "text": "I've now worked through all the material for session 1 (all videos plus 2023 lab and 2024 additional practice) as well as the optional 2024 problem set. By far the most interesting\/challenging exercise is `credit` in the problem set: <https:\/\/cs50.harvard.edu\/x\/2024\/psets\/1\/credit\/>. Even for experienced R programmers, this presents some C-specific technicalities\/gotchas, as well as the opportunity to take advantage of some C-specific features (e.g. truncation and that all numbers other than 0 evaluate to true). I know that `credit` is optional for the C study group, but I'd highly encourage anyone wanting to stretch themselves to give it a go.",
        "team": "T01DW9DLB2A",
        "user_team": "T01DW9DLB2A",
        "source_team": "T01DW9DLB2A",
        "user_profile": {
            "avatar_hash": "c4cd2d45eb7b",
            "image_72": "https:\/\/avatars.slack-edge.com\/2024-02-05\/6583494822997_c4cd2d45eb7bfbf5886a_72.jpg",
            "first_name": "Ella",
            "real_name": "Ella Kaye",
            "display_name": "Ella Kaye",
            "team": "T01DW9DLB2A",
            "name": "ella.kaye",
            "is_restricted": false,
            "is_ultra_restricted": false
        },
        "thread_ts": "1705076353.136199",
        "reply_count": 18,
        "reply_users_count": 3,
        "latest_reply": "1705825964.735619",
        "reply_users": [
            "U06360JH6FP",
            "U035M81N341",
            "U06D8CVMZDG"
        ],
        "replies": [
            {
                "user": "U06360JH6FP",
                "ts": "1705116663.318879"
            },
            {
                "user": "U035M81N341",
                "ts": "1705130999.852589"
            },
            {
                "user": "U06360JH6FP",
                "ts": "1705169608.708539"
            },
            {
                "user": "U035M81N341",
                "ts": "1705221804.845929"
            },
            {
                "user": "U06360JH6FP",
                "ts": "1705246551.897099"
            },
            {
                "user": "U06360JH6FP",
                "ts": "1705246750.467519"
            },
            {
                "user": "U06360JH6FP",
                "ts": "1705246853.827419"
            },
            {
                "user": "U06360JH6FP",
                "ts": "1705247746.183049"
            },
            {
                "user": "U035M81N341",
                "ts": "1705262612.402929"
            },
            {
                "user": "U035M81N341",
                "ts": "1705262784.791609"
            },
            {
                "user": "U06360JH6FP",
                "ts": "1705263013.110829"
            },
            {
                "user": "U06D8CVMZDG",
                "ts": "1705314543.763929"
            },
            {
                "user": "U06360JH6FP",
                "ts": "1705328976.584079"
            },
            {
                "user": "U06D8CVMZDG",
                "ts": "1705663516.836459"
            },
            {
                "user": "U06360JH6FP",
                "ts": "1705737429.072769"
            },
            {
                "user": "U06D8CVMZDG",
                "ts": "1705788073.288849"
            },
            {
                "user": "U06360JH6FP",
                "ts": "1705823891.181559"
            },
            {
                "user": "U035M81N341",
                "ts": "1705825964.735619"
            }
        ],
        "is_locked": false,
        "subscribed": false,
        "attachments": [
            {
                "image_url": "https:\/\/cs50.harvard.edu\/x\/2024\/assets\/sanders.jpg",
                "image_width": 2048,
                "image_height": 1366,
                "image_bytes": 422356,
                "from_url": "https:\/\/cs50.harvard.edu\/x\/2024\/psets\/1\/credit\/",
                "service_icon": "https:\/\/cs50.harvard.edu\/favicon.ico",
                "id": 1,
                "original_url": "https:\/\/cs50.harvard.edu\/x\/2024\/psets\/1\/credit\/",
                "fallback": "Credit - CS50x 2024",
                "text": "Harvard University's introduction to the intellectual enterprises of computer science and the art of programming.",
                "title": "Credit - CS50x 2024",
                "title_link": "https:\/\/cs50.harvard.edu\/x\/2024\/psets\/1\/credit\/",
                "service_name": "cs50.harvard.edu"
            }
        ],
        "blocks": [
            {
                "type": "rich_text",
                "block_id": "IS1+I",
                "elements": [
                    {
                        "type": "rich_text_section",
                        "elements": [
                            {
                                "type": "text",
                                "text": "I've now worked through all the material for session 1 (all videos plus 2023 lab and 2024 additional practice) as well as the optional 2024 problem set. By far the most interesting\/challenging exercise is "
                            },
                            {
                                "type": "text",
                                "text": "credit",
                                "style": {
                                    "code": true
                                }
                            },
                            {
                                "type": "text",
                                "text": " in the problem set: "
                            },
                            {
                                "type": "link",
                                "url": "https:\/\/cs50.harvard.edu\/x\/2024\/psets\/1\/credit\/"
                            },
                            {
                                "type": "text",
                                "text": ". Even for experienced R programmers, this presents some C-specific technicalities\/gotchas, as well as the opportunity to take advantage of some C-specific features (e.g. truncation and that all numbers other than 0 evaluate to true). I know that "
                            },
                            {
                                "type": "text",
                                "text": "credit",
                                "style": {
                                    "code": true
                                }
                            },
                            {
                                "type": "text",
                                "text": " is optional for the C study group, but I'd highly encourage anyone wanting to stretch themselves to give it a go."
                            }
                        ]
                    }
                ]
            }
        ],
        "reactions": [
            {
                "name": "raised_hands",
                "users": [
                    "U06BCU9EY2E"
                ],
                "count": 1
            },
            {
                "name": "+1",
                "users": [
                    "U051N27B1B8",
                    "U06360JH6FP",
                    "U0655E66NSY",
                    "U06BCU9EY2E"
                ],
                "count": 4
            },
            {
                "name": "raised_hands::skin-tone-2",
                "users": [
                    "U01DZUA88S1"
                ],
                "count": 1
            }
        ]
    },
    {
        "user": "U06360JH6FP",
        "type": "message",
        "ts": "1705116663.318879",
        "client_msg_id": "42661ADF-4463-494C-8888-652D079ACB58",
        "text": "<@U035M81N341> BTW the little C idiom of subtracting ‘0’ that you highlighted in the “Advent of Code” post is useful in the Credit programming task.",
        "team": "T01DW9DLB2A",
        "user_team": "T01DW9DLB2A",
        "source_team": "T01DW9DLB2A",
        "user_profile": {
            "avatar_hash": "ccd10a98f3a6",
            "image_72": "https:\/\/avatars.slack-edge.com\/2023-10-28\/6123580324497_ccd10a98f3a6190d4dd5_72.jpg",
            "first_name": "Munawar",
            "real_name": "Munawar Cheema",
            "display_name": "Munawar Cheema",
            "team": "T01DW9DLB2A",
            "name": "munawar.a.cheema",
            "is_restricted": false,
            "is_ultra_restricted": false
        },
        "thread_ts": "1705076353.136199",
        "parent_user_id": "U035M81N341",
        "blocks": [
            {
                "type": "rich_text",
                "block_id": "9N+fK",
                "elements": [
                    {
                        "type": "rich_text_section",
                        "elements": [
                            {
                                "type": "user",
                                "user_id": "U035M81N341"
                            },
                            {
                                "type": "text",
                                "text": " BTW the little C idiom of subtracting ‘0’ that you highlighted in the “Advent of Code” post is useful in the Credit programming task."
                            }
                        ]
                    }
                ]
            }
        ]
    },
    {
        "user": "U035M81N341",
        "type": "message",
        "ts": "1705130999.852589",
        "client_msg_id": "C28D338D-AC9E-475A-BB53-7801E3E65A5A",
        "text": "Ooh, <@U06360JH6FP> I didn't use that for this! It would be interesting to compare approaches.",
        "team": "T01DW9DLB2A",
        "user_team": "T01DW9DLB2A",
        "source_team": "T01DW9DLB2A",
        "user_profile": {
            "avatar_hash": "c4cd2d45eb7b",
            "image_72": "https:\/\/avatars.slack-edge.com\/2024-02-05\/6583494822997_c4cd2d45eb7bfbf5886a_72.jpg",
            "first_name": "Ella",
            "real_name": "Ella Kaye",
            "display_name": "Ella Kaye",
            "team": "T01DW9DLB2A",
            "name": "ella.kaye",
            "is_restricted": false,
            "is_ultra_restricted": false
        },
        "thread_ts": "1705076353.136199",
        "parent_user_id": "U035M81N341",
        "blocks": [
            {
                "type": "rich_text",
                "block_id": "vcsn0",
                "elements": [
                    {
                        "type": "rich_text_section",
                        "elements": [
                            {
                                "type": "text",
                                "text": "Ooh, "
                            },
                            {
                                "type": "user",
                                "user_id": "U06360JH6FP"
                            },
                            {
                                "type": "text",
                                "text": " I didn't use that for this! It would be interesting to compare approaches."
                            }
                        ]
                    }
                ]
            }
        ],
        "reactions": [
            {
                "name": "+1",
                "users": [
                    "U06360JH6FP"
                ],
                "count": 1
            }
        ]
    }
]