[
    {
        "user": "U01DZUA88S1",
        "type": "message",
        "ts": "1716898166.792129",
        "edited": {
            "user": "U01DZUA88S1",
            "ts": "1716898209.000000"
        },
        "client_msg_id": "3abe8e20-bf3b-4d51-adf6-f7ff2377fb0d",
        "text": "For the final session of the C Study Group, we will be looking at the chapter from DeepR. Cohort 1 discussed the exercises (<https:\/\/deepr.gagolewski.com\/chapter\/310-compiled.html#exercises>) in the group session just now and we suggest the following for next time:\n\n• Work through the questions for Exercise 14.29\n• Aim to implement at least one of the functions in Exercise 14.30 with an R front end and a C back end. <@U035M81N341> and <@U04RM6HJ5GT>will implement `rle()` and  <@U060RULT44D> and me will implement `split()`. If we have a go at another one we will report back here - it would be good to have some overlap so we can compare approaches and discuss any difficulties faced.\nThe other exercises are useful, but may not lead to much group discussion, so we can leave these as optional extras.",
        "team": "T01DW9DLB2A",
        "user_team": "T01DW9DLB2A",
        "source_team": "T01DW9DLB2A",
        "user_profile": {
            "avatar_hash": "g580131f5a7a",
            "image_72": "https:\/\/secure.gravatar.com\/avatar\/580131f5a7a4fa33c811dc6d20ab3ef8.jpg?s=72&d=https%3A%2F%2Fa.slack-edge.com%2Fdf10d%2Fimg%2Favatars%2Fava_0004-72.png",
            "first_name": "Heather",
            "real_name": "Heather Turner (she\/her)",
            "display_name": "Heather Turner",
            "team": "T01DW9DLB2A",
            "name": "ht",
            "is_restricted": false,
            "is_ultra_restricted": false
        },
        "blocks": [
            {
                "type": "rich_text",
                "block_id": "xF8y7",
                "elements": [
                    {
                        "type": "rich_text_section",
                        "elements": [
                            {
                                "type": "text",
                                "text": "For the final session of the C Study Group, we will be looking at the chapter from DeepR. Cohort 1 discussed the exercises ("
                            },
                            {
                                "type": "link",
                                "url": "https:\/\/deepr.gagolewski.com\/chapter\/310-compiled.html#exercises"
                            },
                            {
                                "type": "text",
                                "text": ") in the group session just now and we suggest the following for next time:\n\n"
                            }
                        ]
                    },
                    {
                        "type": "rich_text_list",
                        "elements": [
                            {
                                "type": "rich_text_section",
                                "elements": [
                                    {
                                        "type": "text",
                                        "text": "Work through the questions for Exercise 14.29"
                                    }
                                ]
                            },
                            {
                                "type": "rich_text_section",
                                "elements": [
                                    {
                                        "type": "text",
                                        "text": "Aim to implement at least one of the functions in Exercise 14.30 with an R front end and a C back end. "
                                    },
                                    {
                                        "type": "user",
                                        "user_id": "U035M81N341"
                                    },
                                    {
                                        "type": "text",
                                        "text": " and "
                                    },
                                    {
                                        "type": "user",
                                        "user_id": "U04RM6HJ5GT"
                                    },
                                    {
                                        "type": "text",
                                        "text": "will implement "
                                    },
                                    {
                                        "type": "text",
                                        "text": "rle()",
                                        "style": {
                                            "code": true
                                        }
                                    },
                                    {
                                        "type": "text",
                                        "text": " and  "
                                    },
                                    {
                                        "type": "user",
                                        "user_id": "U060RULT44D"
                                    },
                                    {
                                        "type": "text",
                                        "text": " and me will implement "
                                    },
                                    {
                                        "type": "text",
                                        "text": "split()",
                                        "style": {
                                            "code": true
                                        }
                                    },
                                    {
                                        "type": "text",
                                        "text": ". If we have a go at another one we will report back here - it would be good to have some overlap so we can compare approaches and discuss any difficulties faced."
                                    }
                                ]
                            }
                        ],
                        "style": "bullet",
                        "indent": 0,
                        "border": 0
                    },
                    {
                        "type": "rich_text_section",
                        "elements": [
                            {
                                "type": "text",
                                "text": "\nThe other exercises are useful, but may not lead to much group discussion, so we can leave these as optional extras."
                            }
                        ]
                    }
                ]
            }
        ],
        "reactions": [
            {
                "name": "+1",
                "users": [
                    "U060RULT44D"
                ],
                "count": 1
            }
        ]
    },
    {
        "user": "U01DZUA88S1",
        "type": "message",
        "ts": "1716918162.451989",
        "client_msg_id": "70d4688f-92bb-4b63-a4dd-523072ebebc9",
        "text": "In Cohort 2 we noticed there are actually several exercises interweaved in the earlier sections! The earlier exercises are more closely connected to the content in each section, so are a bit more like the exercises we have been used to so far, but without the skeleton code and hints :sweat_smile: I've had a closer look and I think the following may be an equivalent amount of work to the lab + practice problems on the CS50 course:\n\nExercise 14.1 : inspect and load demo R package with C code\nExercise 14.2 : extend the package by adding a C function equivalent to which.max()\nExercise 14.3 : compile some of the demo C functions and write an R function to use them\nExercise 14.4 : implement all() and any() in C.\n\nThere are then several more exercises that work with lists, factors and matrices among other things, even before you get to the Exercises section I linked to before. We might want to come back to these exercises in July\/August as I think most of us won't be able to have a decent go at these in June. How does that sound?",
        "team": "T01DW9DLB2A",
        "user_team": "T01DW9DLB2A",
        "source_team": "T01DW9DLB2A",
        "user_profile": {
            "avatar_hash": "g580131f5a7a",
            "image_72": "https:\/\/secure.gravatar.com\/avatar\/580131f5a7a4fa33c811dc6d20ab3ef8.jpg?s=72&d=https%3A%2F%2Fa.slack-edge.com%2Fdf10d%2Fimg%2Favatars%2Fava_0004-72.png",
            "first_name": "Heather",
            "real_name": "Heather Turner (she\/her)",
            "display_name": "Heather Turner",
            "team": "T01DW9DLB2A",
            "name": "ht",
            "is_restricted": false,
            "is_ultra_restricted": false
        },
        "blocks": [
            {
                "type": "rich_text",
                "block_id": "7SWTv",
                "elements": [
                    {
                        "type": "rich_text_section",
                        "elements": [
                            {
                                "type": "text",
                                "text": "In Cohort 2 we noticed there are actually several exercises interweaved in the earlier sections! The earlier exercises are more closely connected to the content in each section, so are a bit more like the exercises we have been used to so far, but without the skeleton code and hints "
                            },
                            {
                                "type": "emoji",
                                "name": "sweat_smile",
                                "unicode": "1f605"
                            },
                            {
                                "type": "text",
                                "text": " I've had a closer look and I think the following may be an equivalent amount of work to the lab + practice problems on the CS50 course:\n\nExercise 14.1 : inspect and load demo R package with C code\nExercise 14.2 : extend the package by adding a C function equivalent to which.max()\nExercise 14.3 : compile some of the demo C functions and write an R function to use them\nExercise 14.4 : implement all() and any() in C.\n\nThere are then several more exercises that work with lists, factors and matrices among other things, even before you get to the Exercises section I linked to before. We might want to come back to these exercises in July\/August as I think most of us won't be able to have a decent go at these in June. How does that sound?"
                            }
                        ]
                    }
                ]
            }
        ],
        "reactions": [
            {
                "name": "+1",
                "users": [
                    "U035M81N341",
                    "U060RULT44D"
                ],
                "count": 2
            }
        ]
    }
]