[
    {
        "user": "U01DZUA88S1",
        "type": "message",
        "ts": "1704789445.223129",
        "client_msg_id": "bab6cce6-b2e4-4c3d-9599-1599be4c4206",
        "text": ":loudspeaker: Contributor Office Hours, Tuesday January 11\n\nJoin an online Office Hour to\n - discuss how to get started contributing to R\n - get help\/feedback on contributions you are working on\n - look at open bugs\/work on translations together\n\nEMEA\/APAC, 10:00-11:00 UTC: <https:\/\/www.meetup.com\/r-contributors\/events\/298086101\/>\nAMER, 09:30-11:00 PST: <https:\/\/www.meetup.com\/r-contributors\/events\/297947055\/>",
        "team": "T01DW9DLB2A",
        "user_team": "T01DW9DLB2A",
        "source_team": "T01DW9DLB2A",
        "user_profile": {
            "avatar_hash": "g580131f5a7a",
            "image_72": "https:\/\/secure.gravatar.com\/avatar\/580131f5a7a4fa33c811dc6d20ab3ef8.jpg?s=72&d=https%3A%2F%2Fa.slack-edge.com%2Fdf10d%2Fimg%2Favatars%2Fava_0004-72.png",
            "first_name": "Heather",
            "real_name": "Heather Turner (she\/her)",
            "display_name": "Heather Turner",
            "team": "T01DW9DLB2A",
            "name": "ht",
            "is_restricted": false,
            "is_ultra_restricted": false
        },
        "blocks": [
            {
                "type": "rich_text",
                "block_id": "RqvZR",
                "elements": [
                    {
                        "type": "rich_text_section",
                        "elements": [
                            {
                                "type": "emoji",
                                "name": "loudspeaker",
                                "unicode": "1f4e2"
                            },
                            {
                                "type": "text",
                                "text": " Contributor Office Hours, Tuesday January 11\n\nJoin an online Office Hour to\n - discuss how to get started contributing to R\n - get help\/feedback on contributions you are working on\n - look at open bugs\/work on translations together\n\nEMEA\/APAC, 10:00-11:00 UTC: "
                            },
                            {
                                "type": "link",
                                "url": "https:\/\/www.meetup.com\/r-contributors\/events\/298086101\/"
                            },
                            {
                                "type": "text",
                                "text": "\nAMER, 09:30-11:00 PST: "
                            },
                            {
                                "type": "link",
                                "url": "https:\/\/www.meetup.com\/r-contributors\/events\/297947055\/"
                            }
                        ]
                    }
                ]
            }
        ],
        "reactions": [
            {
                "name": "+1",
                "users": [
                    "U03JY0DKAAX",
                    "U0655E66NSY"
                ],
                "count": 2
            }
        ]
    },
    {
        "user": "U01DZUA88S1",
        "type": "message",
        "ts": "1704807485.837459",
        "client_msg_id": "0dcec53a-6fac-426b-8838-47551f5e9d6d",
        "text": ":books: C Study Group schedule is live!\n\nMeeting times:\n• *Cohort 1:* 12 noon - 1 pm Europe\/London.\n• *Cohort 2:* 9 am - 10 am US\/Pacific.\nFirst meeting Tuesday 30 January, then 4th Tuesday of the month, February - June 2024.\n\nSign up on <https:\/\/www.meetup.com\/r-contributors\/> or get calendar details from <https:\/\/contributor.r-project.org\/events\/>.\n\nWork plan: <https:\/\/contributor.r-project.org\/events\/c-study-group-2024\/>.",
        "team": "T01DW9DLB2A",
        "user_team": "T01DW9DLB2A",
        "source_team": "T01DW9DLB2A",
        "user_profile": {
            "avatar_hash": "g580131f5a7a",
            "image_72": "https:\/\/secure.gravatar.com\/avatar\/580131f5a7a4fa33c811dc6d20ab3ef8.jpg?s=72&d=https%3A%2F%2Fa.slack-edge.com%2Fdf10d%2Fimg%2Favatars%2Fava_0004-72.png",
            "first_name": "Heather",
            "real_name": "Heather Turner (she\/her)",
            "display_name": "Heather Turner",
            "team": "T01DW9DLB2A",
            "name": "ht",
            "is_restricted": false,
            "is_ultra_restricted": false
        },
        "blocks": [
            {
                "type": "rich_text",
                "block_id": "g9IdA",
                "elements": [
                    {
                        "type": "rich_text_section",
                        "elements": [
                            {
                                "type": "emoji",
                                "name": "books",
                                "unicode": "1f4da"
                            },
                            {
                                "type": "text",
                                "text": " C Study Group schedule is live!\n\nMeeting times:\n"
                            }
                        ]
                    },
                    {
                        "type": "rich_text_list",
                        "elements": [
                            {
                                "type": "rich_text_section",
                                "elements": [
                                    {
                                        "type": "text",
                                        "text": "Cohort 1:",
                                        "style": {
                                            "bold": true
                                        }
                                    },
                                    {
                                        "type": "text",
                                        "text": " 12 noon - 1 pm Europe\/London."
                                    }
                                ]
                            },
                            {
                                "type": "rich_text_section",
                                "elements": [
                                    {
                                        "type": "text",
                                        "text": "Cohort 2:",
                                        "style": {
                                            "bold": true
                                        }
                                    },
                                    {
                                        "type": "text",
                                        "text": " 9 am - 10 am US\/Pacific."
                                    }
                                ]
                            }
                        ],
                        "style": "bullet",
                        "indent": 0,
                        "border": 0
                    },
                    {
                        "type": "rich_text_section",
                        "elements": [
                            {
                                "type": "text",
                                "text": "\nFirst meeting Tuesday 30 January, then 4th Tuesday of the month, February - June 2024.\n\nSign up on "
                            },
                            {
                                "type": "link",
                                "url": "https:\/\/www.meetup.com\/r-contributors\/"
                            },
                            {
                                "type": "text",
                                "text": " or get calendar details from "
                            },
                            {
                                "type": "link",
                                "url": "https:\/\/contributor.r-project.org\/events\/"
                            },
                            {
                                "type": "text",
                                "text": ".\n\nWork plan: "
                            },
                            {
                                "type": "link",
                                "url": "https:\/\/contributor.r-project.org\/events\/c-study-group-2024\/"
                            },
                            {
                                "type": "text",
                                "text": "."
                            }
                        ]
                    }
                ]
            }
        ]
    }
]